drf_optional_fields/__init__.py
drf_optional_fields/serializers.py
drf_optional_fields/views.py
drf_optional_fields-0.0.1.dist-info/LICENSE
drf_optional_fields-0.0.1.dist-info/METADATA
drf_optional_fields-0.0.1.dist-info/WHEEL
drf_optional_fields-0.0.1.dist-info/top_level.txt
drf_optional_fields-0.0.1.dist-info/RECORD
