Metadata-Version: 2.1
Name: drf-optional-fields
Version: 0.0.1
Summary: A django-restframework extension to dynamically specify the returned field.
Home-page: https://github.com/zzhhss/drf-optional-fields
Author: zzhhss
Author-email: clayhaw@163.com
License: UNKNOWN
Platform: UNKNOWN
Classifier: Programming Language :: Python :: 3
Classifier: License :: OSI Approved :: MIT License
Classifier: Operating System :: OS Independent
Requires-Python: >=3.6
